pymysqlpool/__init__.py
pymysqlpool/connection.py
pymysqlpool/pooled_db.py
pymysql_dbpool-0.0.1.dist-info/LICENSE
pymysql_dbpool-0.0.1.dist-info/METADATA
pymysql_dbpool-0.0.1.dist-info/WHEEL
pymysql_dbpool-0.0.1.dist-info/top_level.txt
pymysql_dbpool-0.0.1.dist-info/RECORD
