Metadata-Version: 2.1
Name: pymysql-dbpool
Version: 0.0.1
Summary: db pool for pymysql
Home-page: UNKNOWN
Author: gengleiming
Author-email: 244277947@qq.com
License: UNKNOWN
Platform: UNKNOWN
Classifier: Programming Language :: Python :: 3
Classifier: License :: OSI Approved :: MIT License
Classifier: Operating System :: OS Independent
